odoo/addons/product_material_attributes/LICENSE
odoo/addons/product_material_attributes/README.rst
odoo/addons/product_material_attributes/__init__.py
odoo/addons/product_material_attributes/__manifest__.py
odoo/addons/product_material_attributes/images/screen.png
odoo/addons/product_material_attributes/models/__init__.py
odoo/addons/product_material_attributes/models/product_template.py
odoo/addons/product_material_attributes/security/ir.model.access.csv
odoo/addons/product_material_attributes/static/description/icon.png
odoo/addons/product_material_attributes/static/description/index.html
odoo/addons/product_material_attributes/views/product_template.xml
odoo_addon_product_material_attributes-16.0.1.0.1.dist-info/METADATA
odoo_addon_product_material_attributes-16.0.1.0.1.dist-info/WHEEL
odoo_addon_product_material_attributes-16.0.1.0.1.dist-info/top_level.txt
odoo_addon_product_material_attributes-16.0.1.0.1.dist-info/RECORD
